LICENSE
MANIFEST.in
README.md
setup.cfg
setup.py
nrs/__init__.py
nrs/fileform.py
nrs/nsisfile.py
nrs.egg-info/PKG-INFO
nrs.egg-info/SOURCES.txt
nrs.egg-info/dependency_links.txt
nrs.egg-info/requires.txt
nrs.egg-info/top_level.txt
nrs/ext/__init__.py
nrs/ext/bzlib/__init__.py
nrs/ext/bzlib/bzlib.c
nrs/ext/bzlib/bzlib.h
nrs/ext/bzlib/bzlib.i
nrs/ext/bzlib/config.h
nrs/ext/bzlib/decompress.c
nrs/ext/bzlib/huffman.c
nrs/ida/__init__.py
nrs/ida/loader.py
nrs/ida/proc.py
nrs/strings/__init__.py
nrs/strings/nsis2.py
nrs/strings/nsis3.py