Metadata-Version: 2.1
Name: nrs
Version: 0.2.5
Summary: NSIS Reversing Suite
Home-page: https://github.com/isra17/nrs
Author: isra17
Author-email: isra017@gmail.com
License-File: LICENSE
